Workbook

Sheet Introduction
D2: Introduction & Information
A5: All previous financial data were taked from Nvidia Annual Reports (Income Statement & Balance Sheet & Cash Flow) - All publicly available
A7: Purpose of creating this model is purely for personal development & practice & curiosity - All forecasted numbers are based on personal analysis & opinion
A9: MODEL AND FINANCIAL DATA DO NOT CONTAIN ANY SENSITIVE DATA & ANY FINANCIAL ADVICE
A11: Please do not publish the model anywhere. But if you are interested in using or developing the model for your personal development & curiosity, feel free
A13: If you`d like to discuss the model or have any questions about assumptions & formulas, please contact me
A15: Enjoy Exploring!
A17: Best Regards,
A18: Berk Tansuker
A20: Github
A21: LinkedIn
A22: E-Mail

Sheet Raw P&L
A1: Years ended | B1: Jan 31, 2021 | C1: Jan 30, 2022 | D1: Jan 29, 2023 | E1: Jan 28, 2024 | F1: Jan 26, 2025
A2: Revenue | B2: 16675 | C2: 26914 | D2: 26974 | E2: 60922 | F2: 130497
A3: Cost of revenue | B3: 6279 | C3: 9439 | D3: 11618 | E3: 16621 | F3: 32639
A4: Gross profit | B4: 10396 | C4: 17475 | D4: 15356 | E4: 44301 | F4: 97858
A5: Operating expenses:
A6: Research and development | B6: 3924 | C6: 5268 | D6: 7339 | E6: 8675 | F6: 12914
A7: Sales, general and administrative | B7: 1940 | C7: 2166 | D7: 2440 | E7: 2654 | F7: 3491
A8: Acquisition termination cost | B8: 0 | C8: 0 | D8: 1353 | E8: 0 | F8: 0
A9: Total operating expenses | B9: 5864 | C9: 7434 | D9: 11132 | E9: 11329 | F9: 16405
A10: Operating income / Income from operations | B10: 4532 | C10: 10041 | D10: 4224 | E10: 32972 | F10: 81453
A11: Interest income | B11: 57 | C11: 29 | D11: 267 | E11: 866 | F11: 1786
A12: Interest expense | B12: -184 | C12: -236 | D12: -262 | E12: -257 | F12: -247
A13: Other, net | B13: 4 | C13: 107 | D13: -48 | E13: 237 | F13: 1034
A14: Other income (expense), net | B14: -123 | C14: -100 | D14: -43 | E14: 846 | F14: 2573
A15: Income before income tax | B15: 4409 | C15: 9941 | D15: 4181 | E15: 33818 | F15: 84026
A16: Income tax expense (benefit) | B16: 77 | C16: 189 | D16: -187 | E16: 4058 | F16: 11146
A17: Net income | B17: 4332 | C17: 9752 | D17: 4368 | E17: 29760 | F17: 72880
A18: Net income per share:
A19: Basic | B19: 1.76 | C19: 3.91 | D19: 0.18 | E19: 1.21 | F19: 2.97
A20: Diluted | B20: 1.73 | C20: 3.85 | D20: 0.17 | E20: 1.19 | F20: 2.94
A21: Weighted average shares used in per share computation:
A22: Basic | B22: 2467 | C22: 2496 | D22: 2487 | E22: 2469 | F22: 2455
A23: Diluted | B23: 2510 | C23: 2535 | D23: 2507 | E23: 2494 | F23: 2480

Sheet Raw Balance Sheet
A1: Years ended | B1: Jan 26, 2020 | C1: Jan 31, 2021 | D1: Jan 30, 2022 | E1: Jan 29, 2023 | F1: Jan 28, 2024 | G1: Jan 26, 2025
A2: ASSETS
A3: Current assets:
A4: Cash and cash equivalents | B4: 10896 | C4: 847 | D4: 1990 | E4: 3389 | F4: 7280 | G4: 8589
A5: Marketable securities | B5: 1 | C5: 10714 | D5: 19218 | E5: 9907 | F5: 18704 | G5: 34621
A6: Accounts receivable, net | B6: 1657 | C6: 2429 | D6: 4650 | E6: 3827 | F6: 9999 | G6: 23065
A7: Inventories | B7: 979 | C7: 1826 | D7: 2605 | E7: 5159 | F7: 5282 | G7: 10080
A8: Prepaid expenses and other current assets | B8: 157 | C8: 239 | D8: 366 | E8: 791 | F8: 3080 | G8: 3771
A9: Total current assets | B9: 13690 | C9: 16055 | D9: 28829 | E9: 23073 | F9: 44345 | G9: 80126
A10: Property and equipment, net | B10: 1674 | C10: 2149 | D10: 2778 | E10: 3807 | F10: 3914 | G10: 6283
A11: Operating lease assets | B11: 618 | C11: 707 | D11: 829 | E11: 1038 | F11: 1346 | G11: 1793
A12: Goodwill | B12: 618 | C12: 4193 | D12: 4349 | E12: 4372 | F12: 4430 | G12: 5188
A13: Intangible assets, net | B13: 49 | C13: 2737 | D13: 2339 | E13: 1676 | F13: 1112 | G13: 807
A14: Deferred income tax assets | B14: 548 | C14: 806 | D14: 1222 | E14: 3396 | F14: 6081 | G14: 10979
A15: Other assets | B15: 118 | C15: 2144 | D15: 3841 | E15: 3820 | F15: 4500 | G15: 6425
A16: Total assets | B16: 17315 | C16: 28791 | D16: 44187 | E16: 41182 | F16: 65728 | G16: 111601
A17: LIABILITIES AND SHAREHOLDERS' EQUITY
A18: Current liabilities:
A19: Accounts payable | B19: 687 | C19: 1201 | D19: 1783 | E19: 1193 | F19: 2699 | G19: 6310
A20: Accrued and other current liabilities | B20: 1097 | C20: 1725 | D20: 2552 | E20: 4120 | F20: 6682 | G20: 11737
A21: Short-term debt | B21: 0 | C21: 999 | D21: 0 | E21: 1250 | F21: 1250 | G21: 0
A22: Total current liabilities | B22: 1784 | C22: 3925 | D22: 4335 | E22: 6563 | F22: 10631 | G22: 18047
A23: Long-term debt | B23: 1991 | C23: 5964 | D23: 10946 | E23: 9703 | F23: 8459 | G23: 8463
A24: Long-term operating lease liabilities | B24: 561 | C24: 634 | D24: 741 | E24: 902 | F24: 1119 | G24: 1519
A25: Other long-term liabilities | B25: 775 | C25: 1375 | D25: 1553 | E25: 1913 | F25: 2541 | G25: 4245
A26: Total liabilities | B26: 5111 | C26: 11898 | D26: 17575 | E26: 19081 | F26: 22750 | G26: 32274
A27: Shareholders' equity:
A28: Preferred stock, $0.001 par value; authorized, none issued | C28: — | D28: — | E28: — | F28: — | G28: —
A29: Common stock, $0.001 par value | B29: 1 | C29: 1 | D29: 3 | E29: 2 | F29: 25 | G29: 24
A30: Additional paid-in capital | B30: 7045 | C30: 8721 | D30: 10385 | E30: 11971 | F30: 13109 | G30: 11237
A31: Treasury Stock | B31: -9814 | C31: -10756 | D31: 0 | E31: 0 | F31: 0 | G31: 0
A32: Accumulated other comprehensive income (loss) | B32: 1 | C32: 19 | D32: -11 | E32: -43 | F32: 27 | G32: 28
A33: Retained earnings | B33: 14971 | C33: 18908 | D33: 16235 | E33: 10171 | F33: 29817 | G33: 68038
A34: Total shareholders' equity | B34: 12204 | C34: 16893 | D34: 26612 | E34: 22101 | F34: 42978 | G34: 79327
A35: Total liabilities and shareholders' equity | B35: 17315 | C35: 28791 | D35: 44187 | E35: 41182 | F35: 65728 | G35: 111601

Sheet Raw Cash Flow
A1: Years ended | B1: Jan 26, 2020 | C1: Jan 31, 2021 | D1: Jan 30, 2022 | E1: Jan 29, 2023 | F1: Jan 28, 2024 | G1: Jan 26, 2025
A2: Cash flows from operating activities:
A3: Net income | B3: 2796 | C3: 4332 | D3: 9752 | E3: 4368 | F3: 29760 | G3: 72880
A4: Stock‑based compensation expense | B4: 844 | C4: 1397 | D4: 2004 | E4: 2709 | F4: 3549 | G4: 4737
A5: Depreciation and amortization | B5: 381 | C5: 1098 | D5: 1174 | E5: 1544 | F5: 1508 | G5: 1864
A6: Deferred income taxes | B6: 18 | C6: -282 | D6: -406 | E6: -2164 | F6: -2489 | G6: -4477
A7: (Gains) losses on non‑marketable equity securities and publicly‑held equity securities, net | B7: 1 | C7: 0 | D7: -100 | E7: 45 | F7: -238 | G7: -1030
A8: Acquisition termination cost | B8: 0 | C8: 0 | D8: 0 | E8: 1353 | F8: 0 | G8: 0
A9: Other | B9: 4 | C9: -20 | D9: 47 | E9: -7 | F9: -278 | G9: -502
A10: Changes in operating assets and liabilities, net of acquisitions:
A11: Accounts receivable | B11: -233 | C11: -550 | D11: -2215 | E11: 822 | F11: -6172 | G11: -13063
A12: Inventories | B12: 597 | C12: -524 | D12: -774 | E12: -2554 | F12: -98 | G12: -4781
A13: Prepaid expenses and other assets | B13: 77 | C13: -394 | D13: -1715 | E13: -1517 | F13: -1522 | G13: -395
A14: Accounts payable | B14: 194 | C14: 312 | D14: 568 | E14: -551 | F14: 1531 | G14: 3357
A15: Accrued and other current liabilities | B15: 54 | C15: 290 | D15: 581 | E15: 1341 | F15: 2025 | G15: 4278
A16: Other long‑term liabilities | B16: 27 | C16: 163 | D16: 192 | E16: 252 | F16: 514 | G16: 1221
A17: Net cash provided by operating activities | B17: 4761 | C17: 5822 | D17: 9108 | E17: 5641 | F17: 28090 | G17: 64089
A18: Cash flows from investing activities:
A19: Proceeds from maturities of marketable securities | B19: 4744 | C19: 8792 | D19: 15197 | E19: 19425 | F19: 9732 | G19: 11195
A20: Proceeds from sales of marketable securities | B20: 3365 | C20: 527 | D20: 1023 | E20: 1806 | F20: 50 | G20: 495
A21: Proceeds from sales of non‑marketable equity securities | B21: 0 | C21: 0 | D21: 0 | E21: 8 | F21: 1 | G21: 171
A22: Purchases of marketable securities | B22: -1461 | C22: -19308 | D22: -24787 | E22: -11897 | F22: -18211 | G22: -26575
A23: Purchases related to property and equipment and intangible assets | B23: -489 | C23: -1128 | D23: -976 | E23: -1833 | F23: -1069 | G23: -3236
A24: Purchases of non‑marketable equity securities | B24: 0 | C24: 0 | D24: 0 | E24: -85 | F24: -862 | G24: -1486
A25: Acquisitions, net of cash acquired | B25: -4 | C25: -8524 | D25: -263 | E25: -49 | F25: -83 | G25: -1007
A26: Other | B26: -10 | C26: -34 | D26: -24 | E26: 0 | F26: -124 | G26: 22
A27: Net cash provided by (used in) investing activities | B27: 6145 | C27: -19675 | D27: -9830 | E27: 7375 | F27: -10566 | G27: -20421
A28: Cash flows from financing activities:
A29: Issuance of debt, net issuance costs | B29: 0 | C29: 4968 | D29: 4977 | E29: 0 | F29: 0 | G29: 0
A30: Proceeds related to employee stock plans | B30: 149 | C30: 194 | D30: 281 | E30: 355 | F30: 403 | G30: 490
A31: Payments related to repurchases of common stock | B31: 0 | C31: 0 | D31: 0 | E31: -10039 | F31: -9533 | G31: -33706
A32: Payments related to tax on restricted stock units | B32: -551 | C32: -942 | D32: -1904 | E32: -1475 | F32: -2783 | G32: -6930
A33: Repayment of debt | B33: 0 | C33: 0 | D33: -1000 | E33: 0 | F33: -1250 | G33: -1250
A34: Dividends paid | B34: -390 | C34: -395 | D34: -399 | E34: -398 | F34: -395 | G34: -834
A35: Principal payments on property and equipment and intangible assets | B35: 0 | C35: -17 | D35: -83 | E35: -58 | F35: -74 | G35: -129
A36: Other | B36: 0 | C36: -4 | D36: -7 | E36: -2 | F36: -1 | G36: 0
A37: Net cash used in financing activities | B37: -792 | C37: 3804 | D37: 1865 | E37: -11617 | F37: -13633 | G37: -42359
A38: Change in cash and cash equivalents | B38: 10114 | C38: -10049 | D38: 1143 | E38: 1399 | F38: 3891 | G38: 1309
A39: Cash and cash equivalents at beginning of period | B39: 782 | C39: 10896 | D39: 847 | E39: 1990 | F39: 3389 | G39: 7280
A40: Cash and cash equivalents at end of period | B40: 10896 | C40: 847 | D40: 1990 | E40: 3389 | F40: 7280 | G40: 8589
A41: Supplemental disclosures of cash flow information:
A42: Cash paid for income taxes, net | B42: 176 | C42: 249 | D42: 396 | E42: 1404 | F42: 6549 | G42: 15118
A43: Cash paid for interest | B43: 54 | C43: 138 | D43: 246 | E43: 254 | F43: 252 | G43: 246

Sheet Financial Model & Forecast
C1: Historical Results | H1: Forecast Period
C2: 2021 | D2: 2022 | E2: 2023 | F2: 2024 | G2: 2025 | H2: 2026 | I2: 2027 | J2: 2028 | K2: 2029 | L2: 2030
A3: Balance Sheet Check | C3: =IFERROR(IF(ABS(C76)>1,"ERROR","OK"),"OK") -> OK | D3: =IFERROR(IF(ABS(D76)>1,"ERROR","OK"),"OK") -> OK | E3: =IFERROR(IF(ABS(E76)>1,"ERROR","OK"),"OK") -> OK | F3: =IFERROR(IF(ABS(F76)>1,"ERROR","OK"),"OK") -> OK | G3: =IFERROR(IF(ABS(G76)>1,"ERROR","OK"),"OK") -> OK | H3: =IFERROR(IF(ABS(H76)>1,"ERROR","OK"),"OK") -> OK | I3: =IFERROR(IF(ABS(I76)>1,"ERROR","OK"),"OK") -> OK | J3: =IFERROR(IF(ABS(J76)>1,"ERROR","OK"),"OK") -> OK | ... L3: =IFERROR(IF(ABS(L76)>1,"ERROR","OK"),"OK") -> OK
A6: Assumptions | C6: 2021 | D6: 2022 | E6: 2023 | F6: 2024 | G6: 2025 | H6: 2026 | I6: 2027 | J6: 2028 | K6: 2029 | L6: 2030
A9: Key Assumptions
A10: Revenue Growth (% Change) | D10: =D34/C34-1 -> 0.61403298 | E10: =E34/D34-1 -> 0.002229323 | F10: =F34/E34-1 -> 1.2585453 | G10: =G34/F34-1 -> 1.1420341 | H10: 0.6 | I10: 0.3 | J10: 0.18 | K10: 0.12 | L10: 0.1
A11: Gross Margin (%) | C11: =C36/C34 -> 0.62344828 | D11: =D36/D34 -> 0.64929033 | E11: =E36/E34 -> 0.56928894 | F11: =F36/F34 -> 0.72717573 | G11: =G36/G34 -> 0.74988697 | H11: 0.74 | I11: 0.72 | J11: 0.7 | K11: 0.68 | L11: 0.68
A12: SG&A (% of Revenue) | C12: =C38/C34 -> 0.11634183 | D12: =D38/D34 -> 0.080478561 | E12: =E38/E34 -> 0.090457478 | F12: =F38/F34 -> 0.043563901 | G12: =G38/G34 -> 0.026751573 | H12: 0.04 | I12: 0.05 | J12: 0.06 | K12: 0.07 | L12: 0.07
A13: Research and Development (% of Revenue) | C13: =C37/C34 -> 0.23532234 | D13: =D37/D34 -> 0.19573456 | E13: =E37/E34 -> 0.27207681 | F13: =F37/F34 -> 0.14239519 | G13: =G37/G34 -> 0.098960129 | H13: 0.11 | I13: 0.13 | J13: 0.15 | K13: 0.15 | L13: 0.17
A14: Other/One-off Opex | C14: =C39 -> 0 | D14: =D39 -> 0 | E14: =E39 -> 1353 | F14: =F39 -> 0 | G14: =G39 -> 0 | H14: 0 | I14: 0 | J14: 0 | K14: 0 | L14: 0
A15: Accounts Receivable (Days) | C15: =C57/C34*C28 -> 53.168516 | D15: =D57/D34*D28 -> 63.061975 | E15: =E57/E34*E28 -> 51.785238 | F15: =F57/F34*F28 -> 59.906684 | G15: =G57/G34*G28 -> 64.512786 | H15: 62 | I15: 62 | J15: 63 | K15: 63 | L15: 63
A16: Inventory (Days) | C16: =C58/C35*C28 -> 106.14588 | D16: =D58/D35*D28 -> 100.73366 | E16: =E58/E35*E28 -> 162.0791 | F16: =F58/F35*F28 -> 115.99362 | G16: =G58/G35*G28 -> 112.72404 | H16: 110 | I16: 108 | J16: 105 | K16: 103 | L16: 100
A17: Accounts Payable (Days) | C17: =C64/C35*C28 -> 69.814461 | D17: =D64/D35*D28 -> 68.947452 | E17: =E64/E35*E28 -> 37.480203 | F17: =F64/F35*F28 -> 59.270501 | G17: =G64/G35*G28 -> 70.564356 | H17: 68 | I17: 68 | J17: 67 | K17: 67 | L17: 67
A18: Capex (% of Revenue) | C18: =-C96/C34 -> 0.067646177 | D18: =-D96/D34 -> 0.036263655 | E18: =-E96/E34 -> 0.067954326 | F18: =-F96/F34 -> 0.017547027 | G18: =-G96/G34 -> 0.024797505 | H18: 0.035 | I18: 0.04 | J18: 0.04 | K18: 0.042 | L18: 0.045
A19: D&A (% of PPE) | C19: =C83/C59 -> 0.51093532 | D19: =D83/D59 -> 0.42260619 | E19: =E83/E59 -> 0.40556869 | F19: =F83/F59 -> 0.3852836 | G19: =G83/G59 -> 0.29667356 | H19: 0.32 | I19: 0.32 | J19: 0.31 | K19: 0.3 | L19: 0.3
A20: Stock-Based Comp % Revenue | C20: =C84/C34 -> 0.083778111 | D20: =D84/D34 -> 0.074459389 | E20: =E84/E34 -> 0.10043004 | F20: =F84/F34 -> 0.058254818 | G20: =G84/G34 -> 0.036299685 | H20: 0.04 | I20: 0.038 | J20: 0.035 | K20: 0.033 | L20: 0.03
A21: Effective Tax Rate (%) | C21: =C45/C44 -> 0.017464278 | D21: =D45/D44 -> 0.019012172 | E21: =E45/E44 -> -0.044726142 | F21: =F45/F44 -> 0.11999527 | G21: =G45/G44 -> 0.13264942 | H21: 0.14 | I21: 0.15 | J21: 0.16 | K21: 0.16 | L21: 0.17
A22: Interest on Cash (%) | C22: =C130/C114 -> 0.0052312775 | D22: =D130/D114 -> 0.034238489 | E22: =E130/E114 -> 0.13417085 | F22: =F130/F114 -> 0.25553261 | G22: =G130/G114 -> 0.24532967 | H22: 0.2 | I22: 0.13 | J22: 0.12 | K22: 0.11 | L22: 0.1
A23: Interest on Debt (%) | C23: =-C131/C126 -> 0.092415871 | D23: =-D131/D126 -> 0.033893437 | E23: =-E131/E126 -> 0.023935684 | F23: =-F131/F126 -> 0.023463891 | G23: =-G131/G126 -> 0.025440313 | H23: 0.03 | I23: 0.03 | J23: 0.03 | K23: 0.03 | L23: 0.03
A24: Buyback Ratio (% of Net Income) | C24: =C106/-C46 -> 0 | D24: =D106/-D46 -> 0 | E24: =E106/-E46 -> 2.2983059 | F24: =F106/-F46 -> 0.3203293 | G24: =G106/-G46 -> 0.46248628 | H24: 0.5 | I24: 0.5 | J24: 0.5 | K24: 0.5 | L24: 0.5
A25: Dividend Payout Ratio | C25: =-C107/C46 -> 0.091181902 | D25: =-D107/D46 -> 0.040914684 | E25: =-E107/E46 -> 0.091117216 | F25: =-F107/F46 -> 0.013272849 | G25: =-G107/G46 -> 0.011443469 | H25: 0.02 | I25: 0.02 | J25: 0.03 | K25: 0.04 | L25: 0.04
A26: Accured Liability (% of Opex) | C26: =C66/C40 -> 0.2941678 | D26: =D66/D40 -> 0.3432876 | E26: =E66/E40 -> 0.3701042 | F26: =F66/F40 -> 0.58981375 | G26: =G66/G40 -> 0.71545261 | H26: 0.7 | I26: 0.65 | J26: 0.6 | K26: 0.6 | L26: 0.6
A27: Debt Issuance (Repayment) | C27: =C104+C105 -> 4968 | D27: =D104+D105 -> 3977 | E27: =E104+E105 -> 0 | F27: =F104+F105 -> -1250 | G27: =G104+G105 -> -1250 | H27: -2000 | I27: -2000 | J27: -1000 | K27: -1000 | L27: -1000
A28: Days in Period | C28: 365 | D28: 365 | E28: 365 | F28: 365 | G28: 365 | H28: 365 | I28: 365 | J28: 365 | K28: 365 | L28: 365
A31: Income Statement | C31: 2021 | D31: 2022 | E31: 2023 | F31: 2024 | G31: 2025 | H31: 2026 | I31: 2027 | J31: 2028 | K31: 2029 | L31: 2030
A34: Net Revenue | C34: ='Raw P&L'!B2 -> 16675 | D34: ='Raw P&L'!C2 -> 26914 | E34: ='Raw P&L'!D2 -> 26974 | F34: ='Raw P&L'!E2 -> 60922 | G34: ='Raw P&L'!F2 -> 130497 | H34: =G34*(1+H10) -> 208795.2 | I34: =H34*(1+I10) -> 271433.76 | J34: =I34*(1+J10) -> 320291.84 | K34: =J34*(1+K10) -> 358726.86 | L34: =K34*(1+L10) -> 394599.54
A35: Cost of Revenue | C35: ='Raw P&L'!B3 -> 6279 | D35: ='Raw P&L'!C3 -> 9439 | E35: ='Raw P&L'!D3 -> 11618 | F35: ='Raw P&L'!E3 -> 16621 | G35: ='Raw P&L'!F3 -> 32639 | H35: =H34*(1-H11) -> 54286.752 | I35: =I34*(1-I11) -> 76001.453 | J35: =J34*(1-J11) -> 96087.551 | K35: =K34*(1-K11) -> 114792.59 | L35: =L34*(1-L11) -> 126271.85
A36: Gross Profit | C36: =C34-C35 -> 10396 | D36: =D34-D35 -> 17475 | E36: =E34-E35 -> 15356 | F36: =F34-F35 -> 44301 | G36: =G34-G35 -> 97858 | H36: =H34-H35 -> 154508.45 | I36: =I34-I35 -> 195432.31 | J36: =J34-J35 -> 224204.29 | ... L36: =L34-L35 -> 268327.69
A37: Research & Development | C37: ='Raw P&L'!B6 -> 3924 | D37: ='Raw P&L'!C6 -> 5268 | E37: ='Raw P&L'!D6 -> 7339 | F37: ='Raw P&L'!E6 -> 8675 | G37: ='Raw P&L'!F6 -> 12914 | H37: =H34*H13 -> 22967.472 | I37: =I34*I13 -> 35286.389 | J37: =J34*J13 -> 48043.776 | K37: =K34*K13 -> 53809.029 | L37: =L34*L13 -> 67081.922
A38: SG&A | C38: ='Raw P&L'!B7 -> 1940 | D38: ='Raw P&L'!C7 -> 2166 | E38: ='Raw P&L'!D7 -> 2440 | F38: ='Raw P&L'!E7 -> 2654 | G38: ='Raw P&L'!F7 -> 3491 | H38: =H34*H12 -> 8351.808 | I38: =I34*I12 -> 13571.688 | J38: =J34*J12 -> 19217.51 | K38: =K34*K12 -> 25110.88 | L38: =L34*L12 -> 27621.968
A39: Other Operating Expenses (Acquisition termination cost ) | C39: ='Raw P&L'!B8 -> 0 | D39: ='Raw P&L'!C8 -> 0 | E39: ='Raw P&L'!D8 -> 1353 | F39: ='Raw P&L'!E8 -> 0 | G39: ='Raw P&L'!F8 -> 0 | H39: =H14 -> 0 | I39: =I14 -> 0 | J39: =J14 -> 0 | K39: =K14 -> 0 | L39: =L14 -> 0
A40: Total Operating Expenses | C40: =SUM(C37:C39) -> 5864 | D40: =SUM(D37:D39) -> 7434 | E40: =SUM(E37:E39) -> 11132 | F40: =SUM(F37:F39) -> 11329 | G40: =SUM(G37:G39) -> 16405 | H40: =SUM(H37:H39) -> 31319.28 | I40: =SUM(I37:I39) -> 48858.077 | J40: =SUM(J37:J39) -> 67261.286 | ... L40: =SUM(L37:L39) -> 94703.89
A41: EBIT (Operating Income) | C41: =C36-C40 -> 4532 | D41: =D36-D40 -> 10041 | E41: =E36-E40 -> 4224 | F41: =F36-F40 -> 32972 | G41: =G36-G40 -> 81453 | H41: =H36-H40 -> 123189.17 | I41: =I36-I40 -> 146574.23 | J41: =J36-J40 -> 156943 | ... L41: =L36-L40 -> 173623.8
A42: Interest (Net) | C42: =C132 -> -127 | D42: =D132 -> -207 | E42: =E132 -> 5 | F42: =F132 -> 609 | G42: =G132 -> 1539 | H42: =H132 -> 1463.91 | I42: =I132 -> 2628.9417 | J42: =J132 -> 4283.1964 | ... L42: =L132 -> 6137.1589
A43: Other Income (Net) | C43: ='Raw P&L'!B13 -> 4 | D43: ='Raw P&L'!C13 -> 107 | E43: ='Raw P&L'!D13 -> -48 | F43: ='Raw P&L'!E13 -> 237 | G43: ='Raw P&L'!F13 -> 1034 | H43: 300 | I43: 300 | J43: 300 | K43: 300 | L43: 300
A44: EBT (Income Before Tax) | C44: =SUM(C41:C43) -> 4409 | D44: =SUM(D41:D43) -> 9941 | E44: =SUM(E41:E43) -> 4181 | F44: =SUM(F41:F43) -> 33818 | G44: =SUM(G41:G43) -> 84026 | H44: =SUM(H41:H43) -> 124953.08 | I44: =SUM(I41:I43) -> 149503.17 | J44: =SUM(J41:J43) -> 161526.2 | ... L44: =SUM(L41:L43) -> 180060.96
A45: Income Tax Expense | C45: ='Raw P&L'!B16 -> 77 | D45: ='Raw P&L'!C16 -> 189 | E45: ='Raw P&L'!D16 -> -187 | F45: ='Raw P&L'!E16 -> 4058 | G45: ='Raw P&L'!F16 -> 11146 | H45: =H44*H21 -> 17493.431 | I45: =I44*I21 -> 22425.476 | J45: =J44*J21 -> 25844.191 | K45: =K44*K21 -> 27319.617 | L45: =L44*L21 -> 30610.363
A46: Net Income | C46: =C44-C45 -> 4332 | D46: =D44-D45 -> 9752 | E46: =E44-E45 -> 4368 | F46: =F44-F45 -> 29760 | G46: =G44-G45 -> 72880 | H46: =H44-H45 -> 107459.65 | I46: =I44-I45 -> 127077.7 | J46: =J44-J45 -> 135682 | ... L46: =L44-L45 -> 149450.6
A48: Model Helper (Cross - Statement) D&A (from CF) | C48: ='Raw Cash Flow'!C5 -> 1098 | D48: ='Raw Cash Flow'!D5 -> 1174 | E48: ='Raw Cash Flow'!E5 -> 1544 | F48: ='Raw Cash Flow'!F5 -> 1508 | G48: ='Raw Cash Flow'!G5 -> 1864 | H48: =H83 -> 2010.56 | I48: =I83 -> 3705.687 | J48: =J83 -> 5806.9 | K48: =K83 -> 7721.0127 | L48: =L83 -> 9924.6673
A49: EBITDA | C49: =C41+C48 -> 5630 | D49: =D41+D48 -> 11215 | E49: =E41+E48 -> 5768 | F49: =F41+F48 -> 34480 | G49: =G41+G48 -> 83317 | H49: =H41+H48 -> 125199.73 | I49: =I41+I48 -> 150279.92 | J49: =J41+J48 -> 162749.9 | ... L49: =L41+L48 -> 183548.47
A52: Balance Sheet | C52: 2021 | D52: 2022 | E52: 2023 | F52: 2024 | G52: 2025 | H52: 2026 | I52: 2027 | J52: 2028 | K52: 2029 | L52: 2030
A55: Assets
A56: Cash | C56: ='Raw Balance Sheet'!C4 -> 847 | D56: ='Raw Balance Sheet'!D4 -> 1990 | E56: ='Raw Balance Sheet'!E4 -> 3389 | F56: ='Raw Balance Sheet'!F4 -> 7280 | G56: ='Raw Balance Sheet'!G4 -> 8589 | H56: =H115 -> 21714.09 | I56: =I115 -> 36809.053 | J56: =J115 -> 50337.641 | K56: =K115 -> 62110.489 | L56: =L115 -> 75489.136
A57: Accounts Receivable | C57: ='Raw Balance Sheet'!C6 -> 2429 | D57: ='Raw Balance Sheet'!D6 -> 4650 | E57: ='Raw Balance Sheet'!E6 -> 3827 | F57: ='Raw Balance Sheet'!F6 -> 9999 | G57: ='Raw Balance Sheet'!G6 -> 23065 | H57: =H34*H15/H28 -> 35466.582 | I57: =I34*I15/I28 -> 46106.556 | J57: =J34*J15/J28 -> 55283.249 | K57: =K34*K15/K28 -> 61917.238 | L57: =L34*L15/L28 -> 68108.962
A58: Inventory | C58: ='Raw Balance Sheet'!C7 -> 1826 | D58: ='Raw Balance Sheet'!D7 -> 2605 | E58: ='Raw Balance Sheet'!E7 -> 5159 | F58: ='Raw Balance Sheet'!F7 -> 5282 | G58: ='Raw Balance Sheet'!G7 -> 10080 | H58: =H35*H16/H28 -> 16360.391 | I58: =I35*I16/I28 -> 22488.101 | J58: =J35*J16/J28 -> 27641.624 | K58: =K35*K16/K28 -> 32393.527 | L58: =L35*L16/L28 -> 34595.028
A59: Property & Equipment | C59: ='Raw Balance Sheet'!C10 -> 2149 | D59: ='Raw Balance Sheet'!D10 -> 2778 | E59: ='Raw Balance Sheet'!E10 -> 3807 | F59: ='Raw Balance Sheet'!F10 -> 3914 | G59: ='Raw Balance Sheet'!G10 -> 6283 | H59: =H138 -> 11580.272 | I59: =I138 -> 18731.935 | J59: =J138 -> 25736.709 | K59: =K138 -> 33082.224 | L59: =L138 -> 40914.536
A60: Other Assets | C60: ='Raw Balance Sheet'!C5+'Raw Balance Sheet'!C8+'Raw Balance Sheet'!C11+'Raw Balance Sheet'!C12+'Raw Balance Sheet'!C13+'Raw Balance Sheet'!C14+'Raw Balance Sheet'!C15 -> 21540 | D60: ='Raw Balance Sheet'!D5+'Raw Balance Sheet'!D8+'Raw Balance Sheet'!D11+'Raw Balance Sheet'!D12+'Raw Balance Sheet'!D13+'Raw Balance Sheet'!D14+'Raw Balance Sheet'!D15 -> 32164 | E60: ='Raw Balance Sheet'!E5+'Raw Balance Sheet'!E8+'Raw Balance Sheet'!E11+'Raw Balance Sheet'!E12+'Raw Balance Sheet'!E13+'Raw Balance Sheet'!E14+'Raw Balance Sheet'!E15 -> 25000 | F60: ='Raw Balance Sheet'!F5+'Raw Balance Sheet'!F8+'Raw Balance Sheet'!F11+'Raw Balance Sheet'!F12+'Raw Balance Sheet'!F13+'Raw Balance Sheet'!F14+'Raw Balance Sheet'!F15 -> 39253 | G60: ='Raw Balance Sheet'!G5+'Raw Balance Sheet'!G8+'Raw Balance Sheet'!G11+'Raw Balance Sheet'!G12+'Raw Balance Sheet'!G13+'Raw Balance Sheet'!G14+'Raw Balance Sheet'!G15 -> 63584 | H60: =G60+((-H97)-H98)-H85+H99+H100+H89+H86-H108+H110 -> 91324.393 | I60: =H60+((-I97)-I98)-I85+I99+I100+I89+I86-I108+I110 -> 126842.07 | J60: =I60+((-J97)-J98)-J85+J99+J100+J89+J86-J108+J110 -> 168979.34 | K60: =J60+((-K97)-K98)-K85+K99+K100+K89+K86-K108+K110 -> 216678.55 | L60: =K60+((-L97)-L98)-L85+L99+L100+L89+L86-L108+L110 -> 270036.35
A61: Total Assets | C61: =SUM(C56:C60) -> 28791 | D61: =SUM(D56:D60) -> 44187 | E61: =SUM(E56:E60) -> 41182 | F61: =SUM(F56:F60) -> 65728 | G61: =SUM(G56:G60) -> 111601 | H61: =SUM(H56:H60) -> 176445.73 | I61: =SUM(I56:I60) -> 250977.71 | J61: =SUM(J56:J60) -> 327978.57 | ... L61: =SUM(L56:L60) -> 489144.01
A63: Liabilities
A64: Accounts Payable | C64: ='Raw Balance Sheet'!C19 -> 1201 | D64: ='Raw Balance Sheet'!D19 -> 1783 | E64: ='Raw Balance Sheet'!E19 -> 1193 | F64: ='Raw Balance Sheet'!F19 -> 2699 | G64: ='Raw Balance Sheet'!G19 -> 6310 | H64: =H35*H17/H28 -> 10113.696 | I64: =I35*I17/I28 -> 14159.175 | J64: =J35*J17/J28 -> 17637.989 | K64: =K35*K17/K28 -> 21071.517 | L64: =L35*L17/L28 -> 23178.669
A65: Debt | C65: ='Raw Balance Sheet'!C21+'Raw Balance Sheet'!C23 -> 6963 | D65: ='Raw Balance Sheet'!D21+'Raw Balance Sheet'!D23 -> 10946 | E65: ='Raw Balance Sheet'!E21+'Raw Balance Sheet'!E23 -> 10953 | F65: ='Raw Balance Sheet'!F21+'Raw Balance Sheet'!F23 -> 9709 | G65: ='Raw Balance Sheet'!G21+'Raw Balance Sheet'!G23 -> 8463 | H65: =G65+H27 -> 6463 | I65: =H65+I27 -> 4463 | J65: =I65+J27 -> 3463 | K65: =J65+K27 -> 2463 | L65: =K65+L27 -> 1463
A66: Accrued Liabilities | C66: ='Raw Balance Sheet'!C20 -> 1725 | D66: ='Raw Balance Sheet'!D20 -> 2552 | E66: ='Raw Balance Sheet'!E20 -> 4120 | F66: ='Raw Balance Sheet'!F20 -> 6682 | G66: ='Raw Balance Sheet'!G20 -> 11737 | H66: =H40*H26 -> 21923.496 | I66: =I40*I26 -> 31757.75 | J66: =J40*J26 -> 40356.771 | K66: =K40*K26 -> 47351.945 | L66: =L40*L26 -> 56822.334
A67: Other Liabilities | C67: ='Raw Balance Sheet'!C24+'Raw Balance Sheet'!C25 -> 2009 | D67: ='Raw Balance Sheet'!D24+'Raw Balance Sheet'!D25 -> 2294 | E67: ='Raw Balance Sheet'!E24+'Raw Balance Sheet'!E25 -> 2815 | F67: ='Raw Balance Sheet'!F24+'Raw Balance Sheet'!F25 -> 3660 | G67: ='Raw Balance Sheet'!G24+'Raw Balance Sheet'!G25 -> 5764 | H67: =G67+H92 -> 7037.5 | I67: =H67+I92 -> 8693.05 | J67: =I67+J92 -> 10845.265 | K67: =J67+K92 -> 13643.145 | L67: =K67+L92 -> 17280.388
A68: Total Liabilities | C68: =SUM(C64:C67) -> 11898 | D68: =SUM(D64:D67) -> 17575 | E68: =SUM(E64:E67) -> 19081 | F68: =SUM(F64:F67) -> 22750 | G68: =SUM(G64:G67) -> 32274 | H68: =SUM(H64:H67) -> 45537.692 | I68: =SUM(I64:I67) -> 59072.975 | J68: =SUM(J64:J67) -> 72303.025 | ... L68: =SUM(L64:L67) -> 98744.391
A70: Shareholder's Equity
A71: Equity Capital | C71: ='Raw Balance Sheet'!C29+'Raw Balance Sheet'!C30+'Raw Balance Sheet'!C31+'Raw Balance Sheet'!C32 -> -2015 | D71: ='Raw Balance Sheet'!D29+'Raw Balance Sheet'!D30+'Raw Balance Sheet'!D31+'Raw Balance Sheet'!D32 -> 10377 | E71: ='Raw Balance Sheet'!E29+'Raw Balance Sheet'!E30+'Raw Balance Sheet'!E31+'Raw Balance Sheet'!E32 -> 11930 | F71: ='Raw Balance Sheet'!F29+'Raw Balance Sheet'!F30+'Raw Balance Sheet'!F31+'Raw Balance Sheet'!F32 -> 13161 | G71: ='Raw Balance Sheet'!G29+'Raw Balance Sheet'!G30+'Raw Balance Sheet'!G31+'Raw Balance Sheet'!G32 -> 11289 | H71: =G71 -> 11289 | I71: =H71 -> 11289 | J71: =I71 -> 11289 | K71: =J71 -> 11289 | L71: =K71 -> 11289
A72: Retained Earnings | C72: ='Raw Balance Sheet'!C33 -> 18908 | D72: ='Raw Balance Sheet'!D33 -> 16235 | E72: ='Raw Balance Sheet'!E33 -> 10171 | F72: ='Raw Balance Sheet'!F33 -> 29817 | G72: ='Raw Balance Sheet'!G33 -> 68038 | H72: =G72+H46+H107+H106 -> 119618.63 | I72: =H72+I46+I107+I106 -> 180615.92 | J72: =I72+J46+J107+J106 -> 244386.47 | K72: =J72+K46+K107+K106 -> 310363.34 | L72: =K72+L46+L107+L106 -> 379110.62
A73: Shareholder's Equity | C73: =SUM(C71:C72) -> 16893 | D73: =SUM(D71:D72) -> 26612 | E73: =SUM(E71:E72) -> 22101 | F73: =SUM(F71:F72) -> 42978 | G73: =SUM(G71:G72) -> 79327 | H73: =SUM(H71:H72) -> 130907.63 | I73: =SUM(I71:I72) -> 191904.92 | J73: =SUM(J71:J72) -> 255675.47 | ... L73: =SUM(L71:L72) -> 390399.62
A74: Total Liabilities & Shareholder's Equity | C74: =C68+C73 -> 28791 | D74: =D68+D73 -> 44187 | E74: =E68+E73 -> 41182 | F74: =F68+F73 -> 65728 | G74: =G68+G73 -> 111601 | H74: =H68+H73 -> 176445.32 | I74: =I68+I73 -> 250977.9 | J74: =J68+J73 -> 327978.49 | ... L74: =L68+L73 -> 489144.01
A76: Check | C76: =C61-C74 -> 0 | D76: =D61-D74 -> 0 | E76: =E61-E74 -> 0 | F76: =F61-F74 -> 0 | G76: =G61-G74 -> 0 | H76: =H61-H74 -> 0.4048 | I76: =I61-I74 -> -0.185824 | J76: =J61-J74 -> 0.0753584 | ... L76: =L61-L74 -> 0.0052402561
A79: Cash Flow Statement | C79: 2021 | D79: 2022 | E79: 2023 | F79: 2024 | G79: 2025 | H79: 2026 | I79: 2027 | J79: 2028 | K79: 2029 | L79: 2030
A81: Operating Cash Flow
A82: Net Income | C82: ='Raw Cash Flow'!C3 -> 4332 | D82: ='Raw Cash Flow'!D3 -> 9752 | E82: ='Raw Cash Flow'!E3 -> 4368 | F82: ='Raw Cash Flow'!F3 -> 29760 | G82: ='Raw Cash Flow'!G3 -> 72880 | H82: =H46 -> 107459.65 | I82: =I46 -> 127077.7 | J82: =J46 -> 135682 | K82: =K46 -> 143427.99 | L82: =L46 -> 149450.6
A83: Depreciation & Amortization | C83: ='Raw Cash Flow'!C5 -> 1098 | D83: ='Raw Cash Flow'!D5 -> 1174 | E83: ='Raw Cash Flow'!E5 -> 1544 | F83: ='Raw Cash Flow'!F5 -> 1508 | G83: ='Raw Cash Flow'!G5 -> 1864 | H83: =H135*H19 -> 2010.56 | I83: =I135*I19 -> 3705.687 | J83: =J135*J19 -> 5806.9 | K83: =K135*K19 -> 7721.0127 | L83: =L135*L19 -> 9924.6673
A84: Stock Based Compensation | C84: ='Raw Cash Flow'!C4 -> 1397 | D84: ='Raw Cash Flow'!D4 -> 2004 | E84: ='Raw Cash Flow'!E4 -> 2709 | F84: ='Raw Cash Flow'!F4 -> 3549 | G84: ='Raw Cash Flow'!G4 -> 4737 | H84: =H34*H20 -> 8351.808 | I84: =I34*I20 -> 10314.483 | J84: =J34*J20 -> 11210.214 | K84: =K34*K20 -> 11837.986 | L84: =L34*L20 -> 11837.986
A85: Deferred Income Taxes | C85: ='Raw Cash Flow'!C6 -> -282 | D85: ='Raw Cash Flow'!D6 -> -406 | E85: ='Raw Cash Flow'!E6 -> -2164 | F85: ='Raw Cash Flow'!F6 -> -2489 | G85: ='Raw Cash Flow'!G6 -> -4477 | H85: =G85*(1+(15/100)) -> -5148.55 | I85: =H85*(1+(15/100)) -> -5920.8325 | J85: =I85*(1+(15/100)) -> -6808.9574 | K85: =J85*(1+(15/100)) -> -7830.301 | L85: =K85*(1+(15/100)) -> -9004.8461
A86: Other Non-Cash Items | C86: ='Raw Cash Flow'!C7+'Raw Cash Flow'!C8+'Raw Cash Flow'!C9 -> -20 | D86: ='Raw Cash Flow'!D7+'Raw Cash Flow'!D8+'Raw Cash Flow'!D9 -> -53 | E86: ='Raw Cash Flow'!E7+'Raw Cash Flow'!E8+'Raw Cash Flow'!E9 -> 1391 | F86: ='Raw Cash Flow'!F7+'Raw Cash Flow'!F8+'Raw Cash Flow'!F9 -> -516 | G86: ='Raw Cash Flow'!G7+'Raw Cash Flow'!G8+'Raw Cash Flow'!G9 -> -1532 | H86: =-H34*0.002 -> -417.5904 | I86: =-I34*0.002 -> -542.86752 | J86: =-J34*0.002 -> -640.58367 | K86: =-K34*0.002 -> -717.45371 | L86: =-L34*0.002 -> -789.19909
A87: Change in Accounts Receivable | C87: ='Raw Cash Flow'!C11 -> -550 | D87: ='Raw Cash Flow'!D11 -> -2215 | E87: ='Raw Cash Flow'!E11 -> 822 | F87: ='Raw Cash Flow'!F11 -> -6172 | G87: ='Raw Cash Flow'!G11 -> -13063 | H87: =-(H141-G141) -> -12401.582 | I87: =-(I141-H141) -> -10639.975 | J87: =-(J141-I141) -> -9176.6921 | K87: =-(K141-J141) -> -6633.9898 | L87: =-(L141-K141) -> -6191.7238
A88: Change in Inventory | C88: ='Raw Cash Flow'!C12 -> -524 | D88: ='Raw Cash Flow'!D12 -> -774 | E88: ='Raw Cash Flow'!E12 -> -2554 | F88: ='Raw Cash Flow'!F12 -> -98 | G88: ='Raw Cash Flow'!G12 -> -4781 | H88: =-(H142-G142) -> -6280.391 | I88: =-(I142-H142) -> -6127.7101 | J88: =-(J142-I142) -> -5153.5232 | K88: =-(K142-J142) -> -4751.9023 | L88: =-(L142-K142) -> -2201.5018
A89: Change in Other Current Assets | C89: ='Raw Cash Flow'!C13 -> -394 | D89: ='Raw Cash Flow'!D13 -> -1715 | E89: ='Raw Cash Flow'!E13 -> -1517 | F89: ='Raw Cash Flow'!F13 -> -1522 | G89: ='Raw Cash Flow'!G13 -> -395 | H89: =-(H144-G144) -> -767.84 | I89: =-(I144-H144) -> -783.1968 | J89: =-(J144-I144) -> -798.86074 | K89: =-(K144-J144) -> -814.83795 | L89: =-(L144-K144) -> -831.13471
A90: Change in Accounts Payable | C90: ='Raw Cash Flow'!C14 -> 312 | D90: ='Raw Cash Flow'!D14 -> 568 | E90: ='Raw Cash Flow'!E14 -> -551 | F90: ='Raw Cash Flow'!F14 -> 1531 | G90: ='Raw Cash Flow'!G14 -> 3357 | H90: =H143-G143 -> 3803.6963 | I90: =I143-H143 -> 4045.4785 | J90: =J143-I143 -> 3478.8141 | K90: =K143-J143 -> 3433.5285 | L90: =L143-K143 -> 2107.1517
A91: Change in Accrued Liabilities | C91: ='Raw Cash Flow'!C15 -> 290 | D91: ='Raw Cash Flow'!D15 -> 581 | E91: ='Raw Cash Flow'!E15 -> 1341 | F91: ='Raw Cash Flow'!F15 -> 2025 | G91: ='Raw Cash Flow'!G15 -> 4278 | H91: =H145-G145 -> 10186.496 | I91: =I145-H145 -> 9834.2539 | J91: =J145-I145 -> 8599.0215 | K91: =K145-J145 -> 6995.1737 | L91: =L145-K145 -> 9470.389
A92: Change in Other Long Term Liabilities | C92: ='Raw Cash Flow'!C16 -> 163 | D92: ='Raw Cash Flow'!D16 -> 192 | E92: ='Raw Cash Flow'!E16 -> 252 | F92: ='Raw Cash Flow'!F16 -> 514 | G92: ='Raw Cash Flow'!G16 -> 1221 | H92: =H149-G149 -> 1273.5 | I92: =I149-H149 -> 1655.55 | J92: =J149-I149 -> 2152.215 | K92: =K149-J149 -> 2797.8795 | L92: =L149-K149 -> 3637.2434
A93: Cash from Operations | C93: =SUM(C82:C92) -> 5822 | D93: =SUM(D82:D92) -> 9108 | E93: =SUM(E82:E92) -> 5641 | F93: =SUM(F82:F92) -> 28090 | G93: =SUM(G82:G92) -> 64089 | H93: =SUM(H82:H92) -> 108069.75 | I93: =SUM(I82:I92) -> 132618.57 | J93: =SUM(J82:J92) -> 144350.55 | ... L93: =SUM(L82:L92) -> 167409.63
A95: Investing Cash Flow
A96: Capex | C96: ='Raw Cash Flow'!C23 -> -1128 | D96: ='Raw Cash Flow'!D23 -> -976 | E96: ='Raw Cash Flow'!E23 -> -1833 | F96: ='Raw Cash Flow'!F23 -> -1069 | G96: ='Raw Cash Flow'!G23 -> -3236 | H96: =-H34*H18 -> -7307.832 | I96: =-I34*I18 -> -10857.35 | J96: =-J34*J18 -> -12811.673 | K96: =-K34*K18 -> -15066.528 | L96: =-L34*L18 -> -17756.979
A97: Purchases of Marketable Securities | C97: ='Raw Cash Flow'!C22 -> -19308 | D97: ='Raw Cash Flow'!D22 -> -24787 | E97: ='Raw Cash Flow'!E22 -> -11897 | F97: ='Raw Cash Flow'!F22 -> -18211 | G97: ='Raw Cash Flow'!G22 -> -26575 | H97: =-H34*0.25 -> -52198.8 | I97: =-I34*0.25 -> -67858.44 | J97: =-J34*0.25 -> -80072.959 | K97: =-K34*0.25 -> -89681.714 | L97: =-L34*0.25 -> -98649.886
A98: Proceeds from Sales / Maturities of Marketable Securities | C98: ='Raw Cash Flow'!C19+'Raw Cash Flow'!C20 -> 9319 | D98: ='Raw Cash Flow'!D19+'Raw Cash Flow'!D20 -> 16220 | E98: ='Raw Cash Flow'!E19+'Raw Cash Flow'!E20 -> 21231 | F98: ='Raw Cash Flow'!F19+'Raw Cash Flow'!F20 -> 9782 | G98: ='Raw Cash Flow'!G19+'Raw Cash Flow'!G20 -> 11690 | H98: =-H97*50% -> 26099.4 | I98: =-I97*50% -> 33929.22 | J98: =-J97*50% -> 40036.48 | K98: =-K97*50% -> 44840.857 | L98: =-L97*50% -> 49324.943
A99: Acquisitions (Net of Cash Acquired) | C99: ='Raw Cash Flow'!C25 -> -8524 | D99: ='Raw Cash Flow'!D25 -> -263 | E99: ='Raw Cash Flow'!E25 -> -49 | F99: ='Raw Cash Flow'!F25 -> -83 | G99: ='Raw Cash Flow'!G25 -> -1007 | H99: -1000 | I99: -1034.3 | J99: -1134 | K99: -1161 | L99: -1273
A100: Other Investing Activities | C100: ='Raw Cash Flow'!C21+'Raw Cash Flow'!C24+'Raw Cash Flow'!C26 -> -34 | D100: ='Raw Cash Flow'!D21+'Raw Cash Flow'!D24+'Raw Cash Flow'!D26 -> -24 | E100: ='Raw Cash Flow'!E21+'Raw Cash Flow'!E24+'Raw Cash Flow'!E26 -> -77 | F100: ='Raw Cash Flow'!F21+'Raw Cash Flow'!F24+'Raw Cash Flow'!F26 -> -985 | G100: ='Raw Cash Flow'!G21+'Raw Cash Flow'!G24+'Raw Cash Flow'!G26 -> -1293 | H100: -637.5 | I100: -1100 | J100: -1150 | K100: -1200 | L100: -1150
A101: Cash from Investing | C101: =SUM(C96:C100) -> -19675 | D101: =SUM(D96:D100) -> -9830 | E101: =SUM(E96:E100) -> 7375 | F101: =SUM(F96:F100) -> -10566 | G101: =SUM(G96:G100) -> -20421 | H101: =SUM(H96:H100) -> -35044.732 | I101: =SUM(I96:I100) -> -46920.87 | J101: =SUM(J96:J100) -> -55132.153 | ... L101: =SUM(L96:L100) -> -69504.922
A103: Financing Cash Flow
A104: Issuance of debt | C104: ='Raw Cash Flow'!C29 -> 4968 | D104: ='Raw Cash Flow'!D29 -> 4977 | E104: ='Raw Cash Flow'!E29 -> 0 | F104: ='Raw Cash Flow'!F29 -> 0 | G104: ='Raw Cash Flow'!G29 -> 0 | H104: 0 | I104: 0 | J104: 0 | K104: 0 | L104: 0
A105: Repayment of Debt | C105: ='Raw Cash Flow'!C33 -> 0 | D105: ='Raw Cash Flow'!D33 -> -1000 | E105: ='Raw Cash Flow'!E33 -> 0 | F105: ='Raw Cash Flow'!F33 -> -1250 | G105: ='Raw Cash Flow'!G33 -> -1250 | H105: =H27 -> -2000 | I105: =I27 -> -2000 | J105: =J27 -> -1000 | K105: =K27 -> -1000 | L105: =L27 -> -1000
A106: Share Purchases (Buybacks) | C106: ='Raw Cash Flow'!C31 -> 0 | D106: ='Raw Cash Flow'!D31 -> 0 | E106: ='Raw Cash Flow'!E31 -> -10039 | F106: ='Raw Cash Flow'!F31 -> -9533 | G106: ='Raw Cash Flow'!G31 -> -33706 | H106: =-H46*H24 -> -53729.824 | I106: =-I46*I24 -> -63538.848 | J106: =-J46*J24 -> -67841.002 | K106: =-K46*K24 -> -71713.994 | L106: =-L46*L24 -> -74725.298
A107: Dividends Paid | C107: ='Raw Cash Flow'!C34 -> -395 | D107: ='Raw Cash Flow'!D34 -> -399 | E107: ='Raw Cash Flow'!E34 -> -398 | F107: ='Raw Cash Flow'!F34 -> -395 | G107: ='Raw Cash Flow'!G34 -> -834 | H107: =-H46*H25 -> -2149.1929 | I107: =-I46*I25 -> -2541.5539 | J107: =-J46*J25 -> -4070.4601 | K107: =-K46*K25 -> -5737.1195 | L107: =-L46*L25 -> -5978.0238
A108: Employee Stock Plan Proceeds | C108: ='Raw Cash Flow'!C30 -> 194 | D108: ='Raw Cash Flow'!D30 -> 281 | E108: ='Raw Cash Flow'!E30 -> 355 | F108: ='Raw Cash Flow'!F30 -> 403 | G108: ='Raw Cash Flow'!G30 -> 490 | H108: =H84*7% -> 584.62656 | I108: =I84*7% -> 722.0138 | J108: =J84*7% -> 784.715 | K108: =K84*7% -> 828.65904 | L108: =L84*7% -> 828.65904
A109: Taxes Paid on RSUs | C109: ='Raw Cash Flow'!C32 -> -942 | D109: ='Raw Cash Flow'!D32 -> -1904 | E109: ='Raw Cash Flow'!E32 -> -1475 | F109: ='Raw Cash Flow'!F32 -> -2783 | G109: ='Raw Cash Flow'!G32 -> -6930 | H109: =-H84*30% -> -2505.5424 | I109: =-I84*30% -> -3094.3449 | J109: =-J84*30% -> -3363.0643 | K109: =-K84*30% -> -3551.3959 | L109: =-L84*30% -> -3551.3959
A110: Other Financing Activities | C110: ='Raw Cash Flow'!C35+'Raw Cash Flow'!C36 -> -21 | D110: ='Raw Cash Flow'!D35+'Raw Cash Flow'!D36 -> -90 | E110: ='Raw Cash Flow'!E35+'Raw Cash Flow'!E36 -> -60 | F110: ='Raw Cash Flow'!F35+'Raw Cash Flow'!F36 -> -75 | G110: ='Raw Cash Flow'!G35+'Raw Cash Flow'!G36 -> -129 | H110: -100 | I110: -150 | J110: -200 | K110: -250 | L110: -100
A111: Cash from Financing | C111: =SUM(C104:C110) -> 3804 | D111: =SUM(D104:D110) -> 1865 | E111: =SUM(E104:E110) -> -11617 | F111: =SUM(F104:F110) -> -13633 | G111: =SUM(G104:G110) -> -42359 | H111: =SUM(H104:H110) -> -59899.932 | I111: =SUM(I104:I110) -> -70602.733 | J111: =SUM(J104:J110) -> -75689.812 | ... L111: =SUM(L104:L110) -> -84526.058
A113: Net Increase (decrease) in Cash | C113: =C93+C101+C111 -> -10049 | D113: =D93+D101+D111 -> 1143 | E113: =E93+E101+E111 -> 1399 | F113: =F93+F101+F111 -> 3891 | G113: =G93+G101+G111 -> 1309 | H113: =H93+H101+H111 -> 13125.09 | I113: =I93+I101+I111 -> 15094.964 | J113: =J93+J101+J111 -> 13528.588 | ... L113: =L93+L101+L111 -> 13378.647
A114: Opening Cash Balance | C114: ='Raw Cash Flow'!C39 -> 10896 | D114: =C115 -> 847 | E114: =D115 -> 1990 | F114: =E115 -> 3389 | G114: =F115 -> 7280 | H114: =G115 -> 8589 | I114: =H115 -> 21714.09 | J114: =I115 -> 36809.053 | K114: =J115 -> 50337.641 | L114: =K115 -> 62110.489
A115: Closing Cash Balance | C115: =SUM(C113:C114) -> 847 | D115: =SUM(D113:D114) -> 1990 | E115: =SUM(E113:E114) -> 3389 | F115: =SUM(F113:F114) -> 7280 | G115: =SUM(G113:G114) -> 8589 | H115: =SUM(H113:H114) -> 21714.09 | I115: =SUM(I113:I114) -> 36809.053 | J115: =SUM(J113:J114) -> 50337.641 | ... L115: =SUM(L113:L114) -> 75489.136
A118: Supporting Schedules/Numbers | C118: 2021 | D118: 2022 | E118: 2023 | F118: 2024 | G118: 2025 | H118: 2026 | I118: 2027 | J118: 2028 | K118: 2029 | L118: 2030
A121: Cash&Interest
A122: Opening Balance | C122: =C114 -> 10896 | D122: =D114 -> 847 | E122: =E114 -> 1990 | F122: =F114 -> 3389 | G122: =G114 -> 7280 | H122: =G123 -> 8589 | I122: =H123 -> 21714.09 | J122: =I123 -> 36809.053 | K122: =J123 -> 50337.641 | L122: =K123 -> 62110.489
A123: Closing Balance | C123: =C115 -> 847 | D123: =D115 -> 1990 | E123: =E115 -> 3389 | F123: =F115 -> 7280 | G123: =G115 -> 8589 | H123: =H115 -> 21714.09 | I123: =I115 -> 36809.053 | J123: =J115 -> 50337.641 | ... L123: =L115 -> 75489.136
A125: Debt&Interest
A126: Opening Debt Balance | C126: ='Raw Balance Sheet'!B23+'Raw Balance Sheet'!B21 -> 1991 | D126: =C127 -> 6963 | E126: =D127 -> 10946 | F126: =E127 -> 10953 | G126: =F127 -> 9709 | H126: =G127 -> 8463 | I126: =H127 -> 6463 | J126: =I127 -> 4463 | K126: =J127 -> 3463 | L126: =K127 -> 2463
A127: Closing Debt Balance | C127: =C65 -> 6963 | D127: =D65 -> 10946 | E127: =E65 -> 10953 | F127: =F65 -> 9709 | G127: =G65 -> 8463 | H127: =H65 -> 6463 | I127: =I65 -> 4463 | J127: =J65 -> 3463 | ... L127: =L65 -> 1463
...

Sheet Historical Statements Mapping
A1: Raw Statement | B1: Raw Line Item | C1: Model Statement | D1: Model Line Item
A2: Income Statement | B2: Revenue | C2: Income Statement | D2: Net Revenue
A3: Income Statement | B3: Cost of revenue | C3: Income Statement | D3: Cost of Revenue
A4: Income Statement | B4: Gross profit | C4: Income Statement | D4: Gross Profit
A5: Income Statement | B5: Research and development | C5: Income Statement | D5: Research & Development
A6: Income Statement | B6: Sales, general and administrative | C6: Income Statement | D6: SG&A
A7: Income Statement | B7: Acquisition termination cost | C7: Income Statement | D7: Other Operating Expenses
A8: Income Statement | B8: Total operating expenses | C8: Income Statement | D8: Total Operating Expenses
A9: Income Statement | B9: Operating income / income from operations | C9: Income Statement | D9: EBIT (Operating Income)
A10: Income Statement | B10: Interest income | C10: Income Statement | D10: Interest (Net)
A11: Income Statement | B11: Interest expense | C11: Income Statement | D11: Interest (Net)
A12: Income Statement | B12: Other, net | C12: Income Statement | D12: Other Income (Net)
... A66: Cash Flow | B66: Other | C66: Cash Flow | D66: Other Financing Activities

Sheet Forecast Statement Formulas
A1: Statement | B1: Line Item | C1: Driver & Calculation
A2: Income Statement | B2: Net Revenue | C2: Revenue_(t-1) * (1 + Revenue Growth)
A3: Income Statement | B3: Cost of Revenue | C3: Revenue * (1 - Gross Margin)
A4: Income Statement | B4: Gross Profit | C4: Net Revenue - Cost of Revenue
A5: Income Statement | B5: Research & Development | C5: Revenue * R&D % of Revenue
A6: Income Statement | B6: SG&A | C6: Revenue * SG&A % of Revenue
A7: Income Statement | B7: Other Operating Expenses | C7: Assumption: Other / One-off Opex
A8: Income Statement | B8: Total Operating Expenses | C8: R&D + SG&A + Other OpEx
A9: Income Statement | B9: EBIT (Operating Income) | C9: Gross Profit - Total Operating Expenses
A10: Income Statement | B10: Interest (Net) | C10: Interest Income - Interest Expense
A11: Income Statement | B11: EBT (Income Before Tax) | C11: EBIT + Interest (Net)
A12: Income Statement | B12: Income Tax Expense | C12: EBT * Effective Tax Rate
... A60: Cash Flow | B60: Closing Cash Balance | C60: Opening Cash + Net Change in Cash

Sheet Assumptions Formulas
A1: Assumption Item | B1: Definition and Correct Application in This Model
A2: Revenue Growth (% Change) | B2: Revenue_t = Revenue_(t-1) * (1 + Revenue Growth)
A3: Gross Margin (%) | B3: Gross Margin = Gross Profit / Revenue → Gross Profit_t = Revenue_t * Gross Margin; Cost of Revenue_t = Revenue_t - Gross Profit_t
A4: SG&A (% of Revenue) | B4: SG&A % = SG&A / Revenue → SG&A_t = Revenue_t * SG&A %
A5: Research and Development (% of Revenue) | B5: R&D % = R&D / Revenue → R&D_t = Revenue_t * R&D %
A6: Other / One-off Opex | B6: Direct input for non-recurring operating expenses
A7: Accounts Receivable (Days) | B7: AR Days = Accounts Receivable / Revenue * Days → Accounts Receivable_t = Revenue_t / Days in Period * AR Days
A8: Inventory (Days) | B8: Inventory Days = Inventory / Cost of Revenue * Days → Inventory_t = Cost of Revenue_t / Days in Period * Inventory Days
A9: Accounts Payable (Days) | B9: AP Days = Accounts Payable / Cost of Revenue * Days → Accounts Payable_t = Cost of Revenue_t / Days in Period * AP Days
A10: Capex (% of Revenue) | B10: Capex % = Capex / Revenue → Capex_t = Revenue_t * Capex %
A11: D&A (% of PPE) | B11: D&A % = Depreciation / PPE → Depreciation_t = PPE_(t-1) * D&A %
A12: Stock-Based Comp (% of Revenue) | B12: SBC % = SBC / Revenue → SBC_t = Revenue_t * SBC %
... A20: Days in Period | B20: Number of days used in working capital calculations (365 for annual model)
